py_config_ai/__init__.py
py_config_ai/cli.py
py_config_ai/configs/__init__.py
py_config_ai/configs/config_types.py
py_config_ai/configs/presets.py
py_config_ai/core/__init__.py
py_config_ai/core/generator.py
py_config_ai/core/key_manager.py
py_config_ai/providers/__init__.py
py_config_ai/providers/anthropic_provider.py
py_config_ai/providers/base.py
py_config_ai/providers/gemini_provider.py
py_config_ai/providers/groq_provider.py
py_config_ai/providers/openai_provider.py
py_config_ai/templates/black.toml
py_config_ai/templates/prettierrc.json
py_config_ai/utils/__init__.py
py_config_ai/utils/file_utils.py
py_config_ai/utils/validation.py
py_config_ai-1.0.0.dist-info/licenses/LICENSE
py_config_ai-1.0.0.dist-info/METADATA
py_config_ai-1.0.0.dist-info/WHEEL
py_config_ai-1.0.0.dist-info/entry_points.txt
py_config_ai-1.0.0.dist-info/top_level.txt
py_config_ai-1.0.0.dist-info/RECORD
