Metadata-Version: 2.4
Name: py-config-ai
Version: 1.0.0
Summary: AI-powered configuration file generator for developers with natural language processing and context-aware generation
Author-email: Sherin Joseph Roy <sherin.joseph2217@gmail.com>
Maintainer-email: Sherin Joseph Roy <sherin.joseph2217@gmail.com>
License: MIT
Project-URL: Homepage, https://github.com/Sherin-SEF-AI/py-config-ai
Project-URL: Documentation, https://sherin-sef-ai.github.io/
Project-URL: Repository, https://github.com/Sherin-SEF-AI/py-config-ai.git
Project-URL: Bug Tracker, https://github.com/Sherin-SEF-AI/py-config-ai/issues
Project-URL: Source Code, https://github.com/Sherin-SEF-AI/py-config-ai
Project-URL: Download, https://pypi.org/project/py-config-ai/#files
Project-URL: Changelog, https://github.com/Sherin-SEF-AI/py-config-ai/blob/main/CHANGELOG.md
Keywords: ai,configuration,generator,developer-tools,automation,autonomous-systems,robotics,natural-language,context-aware
Classifier: Development Status :: 4 - Beta
Classifier: Intended Audience :: Developers
Classifier: License :: OSI Approved :: MIT License
Classifier: Operating System :: OS Independent
Classifier: Programming Language :: Python :: 3
Classifier: Programming Language :: Python :: 3.8
Classifier: Programming Language :: Python :: 3.9
Classifier: Programming Language :: Python :: 3.10
Classifier: Programming Language :: Python :: 3.11
Classifier: Programming Language :: Python :: 3.12
Classifier: Topic :: Software Development :: Libraries :: Python Modules
Classifier: Topic :: Software Development :: Code Generators
Classifier: Topic :: Utilities
Classifier: Topic :: Scientific/Engineering :: Artificial Intelligence
Classifier: Topic :: Software Development :: User Interfaces
Classifier: Topic :: System :: Systems Administration
Classifier: Environment :: Console
Classifier: Framework :: Pytest
Classifier: Typing :: Typed
Requires-Python: >=3.8
License-File: LICENSE
Requires-Dist: typer>=0.9.0
Requires-Dist: rich>=13.0.0
Requires-Dist: halo>=0.0.31
Requires-Dist: keyring>=23.0.0
Requires-Dist: openai>=1.0.0
Requires-Dist: anthropic>=0.7.0
Requires-Dist: google-generativeai>=0.3.0
Requires-Dist: groq>=0.4.0
Requires-Dist: pyyaml>=6.0
Requires-Dist: toml>=0.10.2
Requires-Dist: jsonschema>=4.17.0
Provides-Extra: dev
Requires-Dist: pytest>=7.0.0; extra == "dev"
Requires-Dist: pytest-cov>=4.0.0; extra == "dev"
Requires-Dist: pytest-asyncio>=0.21.0; extra == "dev"
Requires-Dist: pytest-mock>=3.10.0; extra == "dev"
Requires-Dist: black>=23.0.0; extra == "dev"
Requires-Dist: isort>=5.12.0; extra == "dev"
Requires-Dist: flake8>=6.0.0; extra == "dev"
Requires-Dist: mypy>=1.0.0; extra == "dev"
Requires-Dist: ruff>=0.1.0; extra == "dev"
Requires-Dist: pre-commit>=3.0.0; extra == "dev"
Requires-Dist: build>=1.0.0; extra == "dev"
Requires-Dist: twine>=4.0.0; extra == "dev"
Provides-Extra: test
Requires-Dist: pytest>=7.0.0; extra == "test"
Requires-Dist: pytest-cov>=4.0.0; extra == "test"
Requires-Dist: pytest-asyncio>=0.21.0; extra == "test"
Requires-Dist: pytest-mock>=3.10.0; extra == "test"
Provides-Extra: lint
Requires-Dist: black>=23.0.0; extra == "lint"
Requires-Dist: isort>=5.12.0; extra == "lint"
Requires-Dist: flake8>=6.0.0; extra == "lint"
Requires-Dist: mypy>=1.0.0; extra == "lint"
Requires-Dist: ruff>=0.1.0; extra == "lint"
Provides-Extra: docs
Requires-Dist: sphinx>=6.0.0; extra == "docs"
Requires-Dist: sphinx-rtd-theme>=1.2.0; extra == "docs"
Requires-Dist: myst-parser>=1.0.0; extra == "docs"
Dynamic: license-file
